REPTree/__init__.py
REPTree/_version.py
REPTree/cli.py
REPTree/metrics.py
REPTree/node.py
REPTree/pipeline.py
REPTree/preprocessing.py
REPTree/splitter.py
REPTree/tree.py
REPTree/utils.py
REPTree/visualization.py
REPTree/pruning/__init__.py
REPTree/pruning/rep.py
reptree-0.1.0.dist-info/METADATA
reptree-0.1.0.dist-info/WHEEL
reptree-0.1.0.dist-info/entry_points.txt
reptree-0.1.0.dist-info/top_level.txt
reptree-0.1.0.dist-info/RECORD
