Metadata-Version: 2.4
Name: reptree
Version: 0.1.0
Summary: A scikit-learn compatible decision tree implementation with Reduced Error Pruning
Author-email: CDXV <mohamedaminedarraj@gmail.com>
Maintainer-email: CDXV <mohamedaminedarraj@gmail.com>
License: MIT
Project-URL: Homepage, https://github.com/AM1N8/RepTree-ML
Project-URL: Documentation, https://reptree.readthedocs.io
Project-URL: Repository, https://github.com/AM1N8/RepTree-ML
Project-URL: Bug Tracker, https://github.com/AM1N8/RepTree-ML/issues
Keywords: machine-learning,decision-tree,pruning,classification,regression,REPTree
Classifier: Development Status :: 4 - Beta
Classifier: Intended Audience :: Developers
Classifier: Intended Audience :: Science/Research
Classifier: License :: OSI Approved :: MIT License
Classifier: Operating System :: OS Independent
Classifier: Programming Language :: Python :: 3
Classifier: Programming Language :: Python :: 3.9
Classifier: Programming Language :: Python :: 3.10
Classifier: Programming Language :: Python :: 3.11
Classifier: Programming Language :: Python :: 3.12
Classifier: Topic :: Scientific/Engineering :: Artificial Intelligence
Classifier: Topic :: Software Development :: Libraries :: Python Modules
Requires-Python: >=3.9
Requires-Dist: black>=25.11.0
Requires-Dist: flake8>=7.3.0
Requires-Dist: isort>=6.1.0
Requires-Dist: mypy>=1.19.0
Requires-Dist: numpy>=1.21.0
Requires-Dist: rich>=14.2.0
Requires-Dist: typer>=0.20.0
Provides-Extra: viz
Requires-Dist: matplotlib>=3.5.0; extra == "viz"
Requires-Dist: seaborn>=0.12.0; extra == "viz"
Provides-Extra: cli
Requires-Dist: typer[all]>=0.9.0; extra == "cli"
Requires-Dist: loguru>=0.7.0; extra == "cli"
Requires-Dist: rich>=13.0.0; extra == "cli"
Provides-Extra: dev
Requires-Dist: pytest>=7.0.0; extra == "dev"
Requires-Dist: pytest-cov>=4.0.0; extra == "dev"
Requires-Dist: black>=23.0.0; extra == "dev"
Requires-Dist: isort>=5.12.0; extra == "dev"
Requires-Dist: flake8>=6.0.0; extra == "dev"
Requires-Dist: mypy>=1.0.0; extra == "dev"
Requires-Dist: pre-commit>=3.0.0; extra == "dev"
Provides-Extra: docs
Requires-Dist: sphinx>=5.0.0; extra == "docs"
Requires-Dist: sphinx-rtd-theme>=1.2.0; extra == "docs"
Requires-Dist: myst-parser>=1.0.0; extra == "docs"
Provides-Extra: all
Requires-Dist: reptree[cli,dev,docs,viz]; extra == "all"
